{"AphiaID":106740,"url":"https:\/\/www.marinespecies.org\/aphia.php?p=taxdetails&id=106740","scientificname":"Enoplometopidae","authority":"de Saint Laurent, 1988","status":"accepted","unacceptreason":null,"taxonRankID":140,"rank":"Family","valid_AphiaID":106740,"valid_name":"Enoplometopidae","valid_authority":"de Saint Laurent, 1988","parentNameUsageID":106688,"originalNameUsageID":106740,"kingdom":"Animalia","phylum":"Arthropoda","class":"Malacostraca","order":"Decapoda","family":"Enoplometopidae","genus":null,"citation":"DecaNet eds. (2026). DecaNet. Enoplometopidae de Saint Laurent, 1988. Accessed through: World Register of Marine Species at: https:\/\/www.marinespecies.org\/aphia.php?p=taxdetails&id=106740 on 2026-07-17","lsid":"urn:lsid:marinespecies.org:taxname:106740","isMarine":1,"isBrackish":0,"isFreshwater":0,"isTerrestrial":0,"isExtinct":0,"match_type":"exact","modified":"2024-09-16T12:28:32.553Z"}